nip/__init__.py
nip/cli.py
nip/nip.py
nip/commands/__init__.py
nip/commands/add.py
nip/commands/init.py
nip/commands/install.py
nip/commands/remove.py
nip/commands/run.py
nip/config/__init__.py
nip/config/defaults.py
nip/hooks/__init__.py
nip/hooks/gitignore.py
nip/hooks/logger.py
nip/hooks/messages.py
nip/hooks/nipfile.py
nip/hooks/prompts.py
nip/hooks/requirements.py
nip/hooks/setup.py
nip/hooks/venv.py
nip/middleware/__init__.py
nip/middleware/echo.py
nip/middleware/env.py
nip/middleware/nipfile.py
nip/providers/__init__.py
nip/providers/git.py
nip/providers/pip.py
nip/providers/shell.py
nip/providers/virtualenv.py
nip/templates/__init__.py
nip/templates/gitignore.py
nip/templates/setup.py
nip/utils/__init__.py
nip/utils/click.py
nip/utils/decorators.py
nip/utils/formatting.py
nip/utils/packaging.py
nip/utils/path.py
nip/utils/spinner.py
nip.cli-0.3.1.dist-info/DESCRIPTION.rst
nip.cli-0.3.1.dist-info/METADATA
nip.cli-0.3.1.dist-info/RECORD
nip.cli-0.3.1.dist-info/WHEEL
nip.cli-0.3.1.dist-info/entry_points.txt
nip.cli-0.3.1.dist-info/metadata.json
nip.cli-0.3.1.dist-info/top_level.txt
