Metadata-Version: 2.0
Name: nip.cli
Version: 0.3.1
Summary: nip isn't pip
Home-page: https://github.com/RopePy/nip
Author: Duroktar
Author-email: duroktar@gmail.com
License: MIT License
Keywords: nip
Platform: UNKNOWN
Classifier: Development Status :: 2 - Pre-Alpha
Classifier: Intended Audience :: Developers
Classifier: License :: OSI Approved :: MIT License
Classifier: Natural Language :: English
Classifier: Programming Language :: Python :: 3.6
Requires-Dist: pyspin (~=1.1.1)
Requires-Dist: click (~=6.7)
Requires-Dist: venv-tools
Requires-Dist: virtualenv-api (~=2.1.16)
Requires-Dist: packaging (~=16.8)
